{
  "paths": {
    "User": [
      [
        "User",
        "曾工作于",
        "龙森经贸(集团)有限责任公司"
      ],
      [
        "User",
        "毕业于",
        "许昌学院(东校区)-经济与管理学院"
      ],
      [
        "User",
        "住在",
        "北京市丰台区新村街道优豪斯之家公寓(玉泉营店)北京111文化产业园南三环西路111号"
      ],
      [
        "User",
        "出生于",
        "黑龙江省哈尔滨市方正县方正林业局红旗屯"
      ]
    ],
    "PersonEntity": {
      "龙森经贸(集团)有限责任公司": [
        [
          "龙森经贸(集团)有限责任公司",
          "餐厅",
          "王梓楼大酒店(黄河路店)"
        ],
        [
          "龙森经贸(集团)有限责任公司",
          "蛋糕店",
          "克莉丝汀(绿山路店)"
        ],
        [
          "龙森经贸(集团)有限责任公司",
          "运动场所",
          "正一跆拳道(星城分馆)"
        ],
        [
          "龙森经贸(集团)有限责任公司",
          "理发店",
          "卡迪亚造型(张坝路)"
        ],
        [
          "龙森经贸(集团)有限责任公司",
          "洗衣店",
          "洗博士洗护馆(嫩江路)"
        ],
        [
          "龙森经贸(集团)有限责任公司",
          "洗浴中心",
          "大拇指盲人推拿(报慈北路店)"
        ]
      ],
      "许昌学院(东校区)-经济与管理学院": [
        [
          "许昌学院(东校区)-经济与管理学院",
          "餐厅",
          "贵州大排面(满庭芳三楼店)"
        ],
        [
          "许昌学院(东校区)-经济与管理学院",
          "蛋糕店",
          "一麦蛋糕面包"
        ],
        [
          "许昌学院(东校区)-经济与管理学院",
          "数码商城",
          "中国联通"
        ],
        [
          "许昌学院(东校区)-经济与管理学院",
          "便利店",
          "惠生超市(文溯路)"
        ],
        [
          "许昌学院(东校区)-经济与管理学院",
          "书店",
          "大学书店(文溯路)"
        ],
        [
          "许昌学院(东校区)-经济与管理学院",
          "超市",
          "8090超市"
        ],
        [
          "许昌学院(东校区)-经济与管理学院",
          "网吧",
          "景天网络会所"
        ],
        [
          "许昌学院(东校区)-经济与管理学院",
          "培训机构",
          "许昌学院-专业网球培训"
        ],
        [
          "许昌学院(东校区)-经济与管理学院",
          "理发店",
          "f.s格色形象工作室"
        ],
        [
          "许昌学院(东校区)-经济与管理学院",
          "住宅区",
          "天城丽景"
        ],
        [
          "许昌学院(东校区)-经济与管理学院",
          "公交站",
          "许昌学院(公交站)"
        ]
      ],
      "北京市丰台区新村街道优豪斯之家公寓(玉泉营店)北京111文化产业园南三环西路111号": [
        [
          "北京市丰台区新村街道优豪斯之家公寓(玉泉营店)北京111文化产业园南三环西路111号",
          "餐厅",
          "兰州拉面"
        ],
        [
          "北京市丰台区新村街道优豪斯之家公寓(玉泉营店)北京111文化产业园南三环西路111号",
          "家居建材市场",
          "紫光物联智能家居体验厅"
        ],
        [
          "北京市丰台区新村街道优豪斯之家公寓(玉泉营店)北京111文化产业园南三环西路111号",
          "宾馆酒店",
          "城市便捷酒店公寓"
        ]
      ],
      "黑龙江省哈尔滨市方正县方正林业局红旗屯": []
    },
    "NewAdd": [
      [
        "贵州大排面(满庭芳三楼店)",
        "蛋糕店",
        "一麦蛋糕面包"
      ],
      [
        "一麦蛋糕面包",
        "餐厅",
        "贵州大排面(满庭芳三楼店)"
      ],
      [
        "贵州大排面(满庭芳三楼店)",
        "便利店",
        "惠生超市(文溯路)"
      ],
      [
        "惠生超市(文溯路)",
        "餐厅",
        "贵州大排面(满庭芳三楼店)"
      ],
      [
        "贵州大排面(满庭芳三楼店)",
        "书店",
        "大学书店(文溯路)"
      ],
      [
        "大学书店(文溯路)",
        "餐厅",
        "贵州大排面(满庭芳三楼店)"
      ],
      [
        "贵州大排面(满庭芳三楼店)",
        "超市",
        "8090超市"
      ],
      [
        "8090超市",
        "餐厅",
        "贵州大排面(满庭芳三楼店)"
      ],
      [
        "惠生超市(文溯路)",
        "书店",
        "大学书店(文溯路)"
      ],
      [
        "大学书店(文溯路)",
        "便利店",
        "惠生超市(文溯路)"
      ],
      [
        "惠生超市(文溯路)",
        "超市",
        "8090超市"
      ],
      [
        "8090超市",
        "便利店",
        "惠生超市(文溯路)"
      ],
      [
        "大学书店(文溯路)",
        "超市",
        "8090超市"
      ],
      [
        "8090超市",
        "书店",
        "大学书店(文溯路)"
      ],
      [
        "景天网络会所",
        "理发店",
        "f.s格色形象工作室"
      ],
      [
        "f.s格色形象工作室",
        "网吧",
        "景天网络会所"
      ],
      [
        "天城丽景",
        "公交站",
        "许昌学院(公交站)"
      ],
      [
        "许昌学院(公交站)",
        "住宅区",
        "天城丽景"
      ],
      [
        "紫光物联智能家居体验厅",
        "宾馆酒店",
        "城市便捷酒店公寓"
      ],
      [
        "城市便捷酒店公寓",
        "家居建材市场",
        "紫光物联智能家居体验厅"
      ]
    ]
  },
  "entity_description": {
    "User": 200,
    "PersonEntity": {
      "龙森经贸(集团)有限责任公司": {
        "id": "30946803",
        "loc": [
          "120.744128899196",
          "31.6812133021476"
        ],
        "type": "公司"
      },
      "许昌学院(东校区)-经济与管理学院": {
        "id": "24405692",
        "loc": [
          "113.87631427137",
          "34.0482748930207"
        ],
        "type": "大学"
      },
      "北京市丰台区新村街道优豪斯之家公寓(玉泉营店)北京111文化产业园南三环西路111号": {
        "id": "2451009",
        "loc": [
          "116.352545237269",
          "39.8592848289908"
        ],
        "type": "住宅区"
      },
      "黑龙江省哈尔滨市方正县方正林业局红旗屯": {
        "id": "20429929",
        "loc": [
          "129.354447765245",
          "45.8035015860311"
        ],
        "type": "住宅区"
      }
    },
    "OneStepEntity": {
      "王梓楼大酒店(黄河路店)": {
        "id": "31597994",
        "loc": [
          "120.740768",
          "31.675822"
        ],
        "type": "餐厅"
      },
      "克莉丝汀(绿山路店)": {
        "id": "31598007",
        "loc": [
          "120.739527",
          "31.678375"
        ],
        "type": "蛋糕店"
      },
      "正一跆拳道(星城分馆)": {
        "id": "31597852",
        "loc": [
          "120.737042",
          "31.678337"
        ],
        "type": "运动场所"
      },
      "卡迪亚造型(张坝路)": {
        "id": "33569262",
        "loc": [
          "120.737614",
          "31.672336"
        ],
        "type": "理发店"
      },
      "洗博士洗护馆(嫩江路)": {
        "id": "33569255",
        "loc": [
          "120.73556",
          "31.678718"
        ],
        "type": "洗衣店"
      },
      "大拇指盲人推拿(报慈北路店)": {
        "id": "33569178",
        "loc": [
          "120.73442",
          "31.674944"
        ],
        "type": "洗浴中心"
      },
      "贵州大排面(满庭芳三楼店)": {
        "id": "22484480",
        "loc": [
          "113.870555",
          "34.045416"
        ],
        "type": "餐厅"
      },
      "一麦蛋糕面包": {
        "id": "22484438",
        "loc": [
          "113.869877",
          "34.045389"
        ],
        "type": "蛋糕店"
      },
      "中国联通": {
        "id": "23214162",
        "loc": [
          "113.866348",
          "34.040463"
        ],
        "type": "数码商城"
      },
      "惠生超市(文溯路)": {
        "id": "23215019",
        "loc": [
          "113.871132",
          "34.044577"
        ],
        "type": "便利店"
      },
      "大学书店(文溯路)": {
        "id": "23215034",
        "loc": [
          "113.871194",
          "34.045313"
        ],
        "type": "书店"
      },
      "8090超市": {
        "id": "23215070",
        "loc": [
          "113.87115",
          "34.046078"
        ],
        "type": "超市"
      },
      "景天网络会所": {
        "id": "22483932",
        "loc": [
          "113.871516",
          "34.039736"
        ],
        "type": "网吧"
      },
      "许昌学院-专业网球培训": {
        "id": "24405699",
        "loc": [
          "113.868909",
          "34.042602"
        ],
        "type": "培训机构"
      },
      "f.s格色形象工作室": {
        "id": "24019267",
        "loc": [
          "113.870997",
          "34.039508"
        ],
        "type": "理发店"
      },
      "天城丽景": {
        "id": "24267071",
        "loc": [
          "113.869503",
          "34.038573"
        ],
        "type": "住宅区"
      },
      "许昌学院(公交站)": {
        "id": "24405540",
        "loc": [
          "113.869186",
          "34.04007"
        ],
        "type": "公交站"
      },
      "兰州拉面": {
        "id": "2626279",
        "loc": [
          "116.349714",
          "39.854906"
        ],
        "type": "餐厅"
      },
      "紫光物联智能家居体验厅": {
        "id": "2940024",
        "loc": [
          "116.345217",
          "39.853286"
        ],
        "type": "家居建材市场"
      },
      "城市便捷酒店公寓": {
        "id": "2939173",
        "loc": [
          "116.345039",
          "39.85215"
        ],
        "type": "宾馆酒店"
      }
    }
  }
}