{
  "paths": {
    "User": [
      [
        "User",
        "曾工作于",
        "宣化区盐业公司"
      ],
      [
        "User",
        "毕业于",
        "北京科技大学天津学院"
      ],
      [
        "User",
        "住在",
        "北京市丰台区南苑乡益丰大院同鑫公寓树桥路15号"
      ],
      [
        "User",
        "出生于",
        "山西省晋中市介休市义安镇孙家寨村"
      ]
    ],
    "PersonEntity": {
      "宣化区盐业公司": [
        [
          "宣化区盐业公司",
          "家居建材市场",
          "新明厨具卫浴太阳能"
        ],
        [
          "宣化区盐业公司",
          "餐厅",
          "乐然棒骨馆"
        ],
        [
          "宣化区盐业公司",
          "蛋糕店",
          "长城食品糕点直销"
        ],
        [
          "宣化区盐业公司",
          "理发店",
          "好运来美发(宣化盐政管理所西南)"
        ],
        [
          "宣化区盐业公司",
          "医院",
          "补牙拔牙牙科"
        ]
      ],
      "北京科技大学天津学院": [
        [
          "北京科技大学天津学院",
          "药店",
          "津京科大药房"
        ],
        [
          "北京科技大学天津学院",
          "餐厅",
          "东北人家(珠江北环西路)"
        ],
        [
          "北京科技大学天津学院",
          "洗衣店",
          "北京科技大学天津学院洗衣房"
        ],
        [
          "北京科技大学天津学院",
          "便利店",
          "劝宝超市(珠江北环西路)"
        ],
        [
          "北京科技大学天津学院",
          "运动场所",
          "北京科技大学天津学院-五人制足球场"
        ],
        [
          "北京科技大学天津学院",
          "数码商城",
          "中国移动(宝坻宇通指定专营店)"
        ],
        [
          "北京科技大学天津学院",
          "银行",
          "中国邮政储蓄银行(北科大分院)"
        ],
        [
          "北京科技大学天津学院",
          "医院",
          "北京科技大学天津学院医务室"
        ],
        [
          "北京科技大学天津学院",
          "图书馆",
          "北京科技大学天津学院理工图书馆"
        ],
        [
          "北京科技大学天津学院",
          "蛋糕店",
          "康津福西点(珠江北环西路)"
        ],
        [
          "北京科技大学天津学院",
          "花鸟鱼虫市场",
          "满天星"
        ],
        [
          "北京科技大学天津学院",
          "理发店",
          "时尚靓点专业美发"
        ],
        [
          "北京科技大学天津学院",
          "成立时间",
          "2005年"
        ],
        [
          "北京科技大学天津学院",
          "所属地区",
          "天津"
        ],
        [
          "北京科技大学天津学院",
          "校长",
          "王斌"
        ]
      ],
      "北京市丰台区南苑乡益丰大院同鑫公寓树桥路15号": [
        [
          "北京市丰台区南苑乡益丰大院同鑫公寓树桥路15号",
          "数码商城",
          "蓉蓉通讯"
        ],
        [
          "北京市丰台区南苑乡益丰大院同鑫公寓树桥路15号",
          "便利店",
          "老苗超市"
        ],
        [
          "北京市丰台区南苑乡益丰大院同鑫公寓树桥路15号",
          "运动场所",
          "东高地文体活动中心游泳馆"
        ],
        [
          "北京市丰台区南苑乡益丰大院同鑫公寓树桥路15号",
          "餐厅",
          "大众家常菜(树桥路店)"
        ],
        [
          "北京市丰台区南苑乡益丰大院同鑫公寓树桥路15号",
          "蛋糕店",
          "靠谱饼屋"
        ],
        [
          "北京市丰台区南苑乡益丰大院同鑫公寓树桥路15号",
          "超市",
          "联通超市(第六分店)"
        ],
        [
          "北京市丰台区南苑乡益丰大院同鑫公寓树桥路15号",
          "理发店",
          "垚垚理发店"
        ],
        [
          "北京市丰台区南苑乡益丰大院同鑫公寓树桥路15号",
          "住宅区",
          "益丰园小区"
        ]
      ],
      "山西省晋中市介休市义安镇孙家寨村": [
        [
          "山西省晋中市介休市义安镇孙家寨村",
          "餐厅",
          "悦和饭店"
        ],
        [
          "山西省晋中市介休市义安镇孙家寨村",
          "便利店",
          "有昌批发部"
        ],
        [
          "山西省晋中市介休市义安镇孙家寨村",
          "数码商城",
          "鹏诚科技"
        ],
        [
          "山西省晋中市介休市义安镇孙家寨村",
          "超市",
          "庭锴批零超市"
        ],
        [
          "山西省晋中市介休市义安镇孙家寨村",
          "药店",
          "康桥大药房"
        ],
        [
          "山西省晋中市介休市义安镇孙家寨村",
          "家居建材市场",
          "老万锅炉"
        ],
        [
          "山西省晋中市介休市义安镇孙家寨村",
          "中学",
          "义安二中"
        ]
      ]
    },
    "NewAdd": [
      [
        "新明厨具卫浴太阳能",
        "医院",
        "补牙拔牙牙科"
      ],
      [
        "补牙拔牙牙科",
        "家居建材市场",
        "新明厨具卫浴太阳能"
      ],
      [
        "好运来美发(宣化盐政管理所西南)",
        "医院",
        "补牙拔牙牙科"
      ],
      [
        "补牙拔牙牙科",
        "理发店",
        "好运来美发(宣化盐政管理所西南)"
      ],
      [
        "津京科大药房",
        "洗衣店",
        "北京科技大学天津学院洗衣房"
      ],
      [
        "北京科技大学天津学院洗衣房",
        "药店",
        "津京科大药房"
      ],
      [
        "津京科大药房",
        "数码商城",
        "中国移动(宝坻宇通指定专营店)"
      ],
      [
        "中国移动(宝坻宇通指定专营店)",
        "药店",
        "津京科大药房"
      ],
      [
        "津京科大药房",
        "银行",
        "中国邮政储蓄银行(北科大分院)"
      ],
      [
        "中国邮政储蓄银行(北科大分院)",
        "药店",
        "津京科大药房"
      ],
      [
        "津京科大药房",
        "理发店",
        "时尚靓点专业美发"
      ],
      [
        "时尚靓点专业美发",
        "药店",
        "津京科大药房"
      ],
      [
        "北京科技大学天津学院洗衣房",
        "数码商城",
        "中国移动(宝坻宇通指定专营店)"
      ],
      [
        "中国移动(宝坻宇通指定专营店)",
        "洗衣店",
        "北京科技大学天津学院洗衣房"
      ],
      [
        "北京科技大学天津学院洗衣房",
        "银行",
        "中国邮政储蓄银行(北科大分院)"
      ],
      [
        "中国邮政储蓄银行(北科大分院)",
        "洗衣店",
        "北京科技大学天津学院洗衣房"
      ],
      [
        "北京科技大学天津学院洗衣房",
        "理发店",
        "时尚靓点专业美发"
      ],
      [
        "时尚靓点专业美发",
        "洗衣店",
        "北京科技大学天津学院洗衣房"
      ],
      [
        "劝宝超市(珠江北环西路)",
        "图书馆",
        "北京科技大学天津学院理工图书馆"
      ],
      [
        "北京科技大学天津学院理工图书馆",
        "便利店",
        "劝宝超市(珠江北环西路)"
      ],
      [
        "劝宝超市(珠江北环西路)",
        "蛋糕店",
        "康津福西点(珠江北环西路)"
      ],
      [
        "康津福西点(珠江北环西路)",
        "便利店",
        "劝宝超市(珠江北环西路)"
      ],
      [
        "劝宝超市(珠江北环西路)",
        "花鸟鱼虫市场",
        "满天星"
      ],
      [
        "满天星",
        "便利店",
        "劝宝超市(珠江北环西路)"
      ],
      [
        "中国移动(宝坻宇通指定专营店)",
        "银行",
        "中国邮政储蓄银行(北科大分院)"
      ],
      [
        "中国邮政储蓄银行(北科大分院)",
        "数码商城",
        "中国移动(宝坻宇通指定专营店)"
      ],
      [
        "中国移动(宝坻宇通指定专营店)",
        "理发店",
        "时尚靓点专业美发"
      ],
      [
        "时尚靓点专业美发",
        "数码商城",
        "中国移动(宝坻宇通指定专营店)"
      ],
      [
        "中国邮政储蓄银行(北科大分院)",
        "理发店",
        "时尚靓点专业美发"
      ],
      [
        "时尚靓点专业美发",
        "银行",
        "中国邮政储蓄银行(北科大分院)"
      ],
      [
        "康津福西点(珠江北环西路)",
        "花鸟鱼虫市场",
        "满天星"
      ],
      [
        "满天星",
        "蛋糕店",
        "康津福西点(珠江北环西路)"
      ],
      [
        "蓉蓉通讯",
        "超市",
        "联通超市(第六分店)"
      ],
      [
        "联通超市(第六分店)",
        "数码商城",
        "蓉蓉通讯"
      ],
      [
        "大众家常菜(树桥路店)",
        "理发店",
        "垚垚理发店"
      ],
      [
        "垚垚理发店",
        "餐厅",
        "大众家常菜(树桥路店)"
      ],
      [
        "悦和饭店",
        "家居建材市场",
        "老万锅炉"
      ],
      [
        "老万锅炉",
        "餐厅",
        "悦和饭店"
      ],
      [
        "有昌批发部",
        "数码商城",
        "鹏诚科技"
      ],
      [
        "鹏诚科技",
        "便利店",
        "有昌批发部"
      ],
      [
        "有昌批发部",
        "药店",
        "康桥大药房"
      ],
      [
        "康桥大药房",
        "便利店",
        "有昌批发部"
      ],
      [
        "鹏诚科技",
        "超市",
        "庭锴批零超市"
      ],
      [
        "庭锴批零超市",
        "数码商城",
        "鹏诚科技"
      ],
      [
        "鹏诚科技",
        "药店",
        "康桥大药房"
      ],
      [
        "康桥大药房",
        "数码商城",
        "鹏诚科技"
      ],
      [
        "庭锴批零超市",
        "药店",
        "康桥大药房"
      ],
      [
        "康桥大药房",
        "超市",
        "庭锴批零超市"
      ]
    ]
  },
  "entity_description": {
    "User": 331,
    "PersonEntity": {
      "宣化区盐业公司": {
        "id": "18143653",
        "loc": [
          "115.046099625294",
          "40.5854116725247"
        ],
        "type": "公司"
      },
      "北京科技大学天津学院": {
        "id": "54134415",
        "loc": [
          "117.402099653335",
          "39.5514818783343"
        ],
        "type": "大学"
      },
      "北京市丰台区南苑乡益丰大院同鑫公寓树桥路15号": {
        "id": "2903425",
        "loc": [
          "116.422954777501",
          "39.8171906463156"
        ],
        "type": "住宅区"
      },
      "山西省晋中市介休市义安镇孙家寨村": {
        "id": "47051370",
        "loc": [
          "111.979417348925",
          "37.1252168165881"
        ],
        "type": "住宅区"
      }
    },
    "OneStepEntity": {
      "新明厨具卫浴太阳能": {
        "id": "18932802",
        "loc": [
          "115.038663",
          "40.579841"
        ],
        "type": "家居建材市场"
      },
      "乐然棒骨馆": {
        "id": "18408287",
        "loc": [
          "115.0425",
          "40.576404"
        ],
        "type": "餐厅"
      },
      "长城食品糕点直销": {
        "id": "18408342",
        "loc": [
          "115.040263",
          "40.580622"
        ],
        "type": "蛋糕店"
      },
      "好运来美发(宣化盐政管理所西南)": {
        "id": "19636923",
        "loc": [
          "115.038082",
          "40.578"
        ],
        "type": "理发店"
      },
      "补牙拔牙牙科": {
        "id": "20075667",
        "loc": [
          "115.038411",
          "40.579438"
        ],
        "type": "医院"
      },
      "津京科大药房": {
        "id": "54165656",
        "loc": [
          "117.390882",
          "39.54619"
        ],
        "type": "药店"
      },
      "东北人家(珠江北环西路)": {
        "id": "53769907",
        "loc": [
          "117.397346",
          "39.543667"
        ],
        "type": "餐厅"
      },
      "北京科技大学天津学院洗衣房": {
        "id": "54034543",
        "loc": [
          "117.390751",
          "39.546173"
        ],
        "type": "洗衣店"
      },
      "劝宝超市(珠江北环西路)": {
        "id": "53908347",
        "loc": [
          "117.395436",
          "39.543444"
        ],
        "type": "便利店"
      },
      "北京科技大学天津学院-五人制足球场": {
        "id": "53770020",
        "loc": [
          "117.39679",
          "39.545408"
        ],
        "type": "运动场所"
      },
      "中国移动(宝坻宇通指定专营店)": {
        "id": "53908344",
        "loc": [
          "117.390804",
          "39.54586"
        ],
        "type": "数码商城"
      },
      "中国邮政储蓄银行(北科大分院)": {
        "id": "54086935",
        "loc": [
          "117.390388",
          "39.545089"
        ],
        "type": "银行"
      },
      "北京科技大学天津学院医务室": {
        "id": "54165655",
        "loc": [
          "117.393005",
          "39.54362"
        ],
        "type": "医院"
      },
      "北京科技大学天津学院理工图书馆": {
        "id": "54133719",
        "loc": [
          "117.394706",
          "39.543843"
        ],
        "type": "图书馆"
      },
      "康津福西点(珠江北环西路)": {
        "id": "53770479",
        "loc": [
          "117.396242",
          "39.543538"
        ],
        "type": "蛋糕店"
      },
      "满天星": {
        "id": "53908346",
        "loc": [
          "117.395665",
          "39.543466"
        ],
        "type": "花鸟鱼虫市场"
      },
      "时尚靓点专业美发": {
        "id": "54034542",
        "loc": [
          "117.390859",
          "39.545844"
        ],
        "type": "理发店"
      },
      "蓉蓉通讯": {
        "id": "2905268",
        "loc": [
          "116.415194",
          "39.812592"
        ],
        "type": "数码商城"
      },
      "老苗超市": {
        "id": "2903433",
        "loc": [
          "116.417092",
          "39.812847"
        ],
        "type": "便利店"
      },
      "东高地文体活动中心游泳馆": {
        "id": "2641557",
        "loc": [
          "116.417347",
          "39.806868"
        ],
        "type": "运动场所"
      },
      "大众家常菜(树桥路店)": {
        "id": "2633047",
        "loc": [
          "116.421978",
          "39.811415"
        ],
        "type": "餐厅"
      },
      "靠谱饼屋": {
        "id": "2634139",
        "loc": [
          "116.418472",
          "39.809983"
        ],
        "type": "蛋糕店"
      },
      "联通超市(第六分店)": {
        "id": "2987941",
        "loc": [
          "116.415358",
          "39.813305"
        ],
        "type": "超市"
      },
      "垚垚理发店": {
        "id": "3194982",
        "loc": [
          "116.421286",
          "39.811261"
        ],
        "type": "理发店"
      },
      "益丰园小区": {
        "id": "3320749",
        "loc": [
          "116.416296",
          "39.809556"
        ],
        "type": "住宅区"
      },
      "悦和饭店": {
        "id": "47326270",
        "loc": [
          "111.97583",
          "37.115726"
        ],
        "type": "餐厅"
      },
      "有昌批发部": {
        "id": "47593505",
        "loc": [
          "111.974825",
          "37.120163"
        ],
        "type": "便利店"
      },
      "鹏诚科技": {
        "id": "47593502",
        "loc": [
          "111.975069",
          "37.118847"
        ],
        "type": "数码商城"
      },
      "庭锴批零超市": {
        "id": "47593501",
        "loc": [
          "111.9753",
          "37.117983"
        ],
        "type": "超市"
      },
      "康桥大药房": {
        "id": "48143781",
        "loc": [
          "111.974786",
          "37.119234"
        ],
        "type": "药店"
      },
      "老万锅炉": {
        "id": "47592482",
        "loc": [
          "111.976116",
          "37.116424"
        ],
        "type": "家居建材市场"
      },
      "义安二中": {
        "id": "48078771",
        "loc": [
          "111.976775",
          "37.11918"
        ],
        "type": "中学"
      }
    }
  }
}