{
  "paths": {
    "User": [
      [
        "User",
        "曾工作于",
        "千年城市规划工程设计公司西区"
      ],
      [
        "User",
        "毕业于",
        "黑龙江科技大学"
      ],
      [
        "User",
        "住在",
        "宁夏回族自治区银川市永宁县望远镇立业春城三区15号楼立业春城望远大道16号"
      ],
      [
        "User",
        "出生于",
        "黑龙江省鸡西市鸡冠区红星乡小鸡冠山鸡密南路1号"
      ]
    ],
    "PersonEntity": {
      "千年城市规划工程设计公司西区": [
        [
          "千年城市规划工程设计公司西区",
          "公交站",
          "都会路向阳路(公交站)"
        ],
        [
          "千年城市规划工程设计公司西区",
          "餐厅",
          "启可咖啡"
        ]
      ],
      "黑龙江科技大学": [
        [
          "黑龙江科技大学",
          "药店",
          "启康百姓医药(康平药店)"
        ],
        [
          "黑龙江科技大学",
          "洗衣店",
          "赛维干洗(哈尔滨店)"
        ],
        [
          "黑龙江科技大学",
          "理发店",
          "蓝火造型(黑科技大学馨园店)"
        ],
        [
          "黑龙江科技大学",
          "餐厅",
          "雕刻时光饮吧(科技大学店)"
        ],
        [
          "黑龙江科技大学",
          "蛋糕店",
          "甜点e派烘焙工坊(顺通大道)"
        ],
        [
          "黑龙江科技大学",
          "网吧",
          "乐枫网吧"
        ],
        [
          "黑龙江科技大学",
          "运动场所",
          "黑龙江科技大学篮球场"
        ],
        [
          "黑龙江科技大学",
          "书店",
          "淘书堡"
        ],
        [
          "黑龙江科技大学",
          "成立时间",
          "1947年"
        ],
        [
          "黑龙江科技大学",
          "所属地区",
          "哈尔滨"
        ],
        [
          "黑龙江科技大学",
          "校长",
          "郝传波"
        ],
        [
          "黑龙江科技大学",
          "知名校友",
          "葛世荣"
        ],
        [
          "黑龙江科技大学",
          "校训",
          "厚德博学、强吾兴邦"
        ]
      ],
      "宁夏回族自治区银川市永宁县望远镇立业春城三区15号楼立业春城望远大道16号": [
        [
          "宁夏回族自治区银川市永宁县望远镇立业春城三区15号楼立业春城望远大道16号",
          "餐厅",
          "何老五"
        ],
        [
          "宁夏回族自治区银川市永宁县望远镇立业春城三区15号楼立业春城望远大道16号",
          "家居建材市场",
          "万昊新"
        ],
        [
          "宁夏回族自治区银川市永宁县望远镇立业春城三区15号楼立业春城望远大道16号",
          "便利店",
          "永福兴商店"
        ],
        [
          "宁夏回族自治区银川市永宁县望远镇立业春城三区15号楼立业春城望远大道16号",
          "数码商城",
          "明佳办公设备服务部"
        ]
      ],
      "黑龙江省鸡西市鸡冠区红星乡小鸡冠山鸡密南路1号": []
    },
    "NewAdd": [
      [
        "启康百姓医药(康平药店)",
        "洗衣店",
        "赛维干洗(哈尔滨店)"
      ],
      [
        "赛维干洗(哈尔滨店)",
        "药店",
        "启康百姓医药(康平药店)"
      ],
      [
        "启康百姓医药(康平药店)",
        "理发店",
        "蓝火造型(黑科技大学馨园店)"
      ],
      [
        "蓝火造型(黑科技大学馨园店)",
        "药店",
        "启康百姓医药(康平药店)"
      ],
      [
        "启康百姓医药(康平药店)",
        "蛋糕店",
        "甜点e派烘焙工坊(顺通大道)"
      ],
      [
        "甜点e派烘焙工坊(顺通大道)",
        "药店",
        "启康百姓医药(康平药店)"
      ],
      [
        "赛维干洗(哈尔滨店)",
        "理发店",
        "蓝火造型(黑科技大学馨园店)"
      ],
      [
        "蓝火造型(黑科技大学馨园店)",
        "洗衣店",
        "赛维干洗(哈尔滨店)"
      ],
      [
        "赛维干洗(哈尔滨店)",
        "蛋糕店",
        "甜点e派烘焙工坊(顺通大道)"
      ],
      [
        "甜点e派烘焙工坊(顺通大道)",
        "洗衣店",
        "赛维干洗(哈尔滨店)"
      ],
      [
        "蓝火造型(黑科技大学馨园店)",
        "蛋糕店",
        "甜点e派烘焙工坊(顺通大道)"
      ],
      [
        "甜点e派烘焙工坊(顺通大道)",
        "理发店",
        "蓝火造型(黑科技大学馨园店)"
      ],
      [
        "永福兴商店",
        "数码商城",
        "明佳办公设备服务部"
      ],
      [
        "明佳办公设备服务部",
        "便利店",
        "永福兴商店"
      ]
    ]
  },
  "entity_description": {
    "User": 687,
    "PersonEntity": {
      "千年城市规划工程设计公司西区": {
        "id": "45534877",
        "loc": [
          "121.423866568174",
          "31.077826716112"
        ],
        "type": "公司"
      },
      "黑龙江科技大学": {
        "id": "21371632",
        "loc": [
          "126.660535053878",
          "45.8251931544098"
        ],
        "type": "大学"
      },
      "宁夏回族自治区银川市永宁县望远镇立业春城三区15号楼立业春城望远大道16号": {
        "id": "40321394",
        "loc": [
          "106.275112512052",
          "38.3919969321566"
        ],
        "type": "住宅区"
      },
      "黑龙江省鸡西市鸡冠区红星乡小鸡冠山鸡密南路1号": {
        "id": "20513379",
        "loc": [
          "131.024232816973",
          "45.2665212494599"
        ],
        "type": "住宅区"
      }
    },
    "OneStepEntity": {
      "都会路向阳路(公交站)": {
        "id": "46647955",
        "loc": [
          "121.417984",
          "31.068182"
        ],
        "type": "公交站"
      },
      "启可咖啡": {
        "id": "45787485",
        "loc": [
          "121.417572",
          "31.073622"
        ],
        "type": "餐厅"
      },
      "启康百姓医药(康平药店)": {
        "id": "21434879",
        "loc": [
          "126.657377",
          "45.820686"
        ],
        "type": "药店"
      },
      "赛维干洗(哈尔滨店)": {
        "id": "21195265",
        "loc": [
          "126.657564",
          "45.821113"
        ],
        "type": "洗衣店"
      },
      "蓝火造型(黑科技大学馨园店)": {
        "id": "21195300",
        "loc": [
          "126.65742",
          "45.821424"
        ],
        "type": "理发店"
      },
      "雕刻时光饮吧(科技大学店)": {
        "id": "20608830",
        "loc": [
          "126.658637",
          "45.822033"
        ],
        "type": "餐厅"
      },
      "甜点e派烘焙工坊(顺通大道)": {
        "id": "20608766",
        "loc": [
          "126.656967",
          "45.820568"
        ],
        "type": "蛋糕店"
      },
      "乐枫网吧": {
        "id": "20608663",
        "loc": [
          "126.652354",
          "45.815703"
        ],
        "type": "网吧"
      },
      "黑龙江科技大学篮球场": {
        "id": "20608829",
        "loc": [
          "126.655272",
          "45.82163"
        ],
        "type": "运动场所"
      },
      "淘书堡": {
        "id": "21000555",
        "loc": [
          "126.650965",
          "45.815637"
        ],
        "type": "书店"
      },
      "何老五": {
        "id": "40415946",
        "loc": [
          "106.26543",
          "38.382637"
        ],
        "type": "餐厅"
      },
      "万昊新": {
        "id": "40479193",
        "loc": [
          "106.273251",
          "38.387569"
        ],
        "type": "家居建材市场"
      },
      "永福兴商店": {
        "id": "40480282",
        "loc": [
          "106.272398",
          "38.383684"
        ],
        "type": "便利店"
      },
      "明佳办公设备服务部": {
        "id": "40476347",
        "loc": [
          "106.27188",
          "38.384304"
        ],
        "type": "数码商城"
      }
    }
  }
}