{
  "paths": {
    "User": [
      [
        "User",
        "曾工作于",
        "北京快乐茄信息技术有限公司"
      ],
      [
        "User",
        "毕业于",
        "西安国际商务进修学院心理学院"
      ],
      [
        "User",
        "住在",
        "北京市昌平区南邵镇双营西路66号院北京风景何营村中街16号"
      ],
      [
        "User",
        "出生于",
        "黑龙江省哈尔滨市道里区尚志街道麦凯乐国际公寓麦凯乐(哈尔滨总店)石头道街109号"
      ]
    ],
    "PersonEntity": {
      "北京快乐茄信息技术有限公司": [
        [
          "北京快乐茄信息技术有限公司",
          "便利店",
          "百佳利社区便民超市"
        ],
        [
          "北京快乐茄信息技术有限公司",
          "超市",
          "首钢餐饮第72商亭"
        ],
        [
          "北京快乐茄信息技术有限公司",
          "餐厅",
          "聚瑞祥美国加州牛肉面大王(上地科实大厦店)"
        ],
        [
          "北京快乐茄信息技术有限公司",
          "成立时间",
          "2015年"
        ]
      ],
      "西安国际商务进修学院心理学院": [
        [
          "西安国际商务进修学院心理学院",
          "餐厅",
          "老实人饺子馆"
        ],
        [
          "西安国际商务进修学院心理学院",
          "网吧",
          "乐游网咖"
        ],
        [
          "西安国际商务进修学院心理学院",
          "蛋糕店",
          "百利甜蛋糕"
        ]
      ],
      "北京市昌平区南邵镇双营西路66号院北京风景何营村中街16号": [
        [
          "北京市昌平区南邵镇双营西路66号院北京风景何营村中街16号",
          "家居建材市场",
          "床上用品棉被窗帘"
        ],
        [
          "北京市昌平区南邵镇双营西路66号院北京风景何营村中街16号",
          "餐厅",
          "豫南风味小吃(昌崔路)"
        ],
        [
          "北京市昌平区南邵镇双营西路66号院北京风景何营村中街16号",
          "医院",
          "博济堂门诊"
        ],
        [
          "北京市昌平区南邵镇双营西路66号院北京风景何营村中街16号",
          "公交站",
          "何营(公交站)"
        ],
        [
          "北京市昌平区南邵镇双营西路66号院北京风景何营村中街16号",
          "住宅区",
          "双营西路68号院"
        ],
        [
          "北京市昌平区南邵镇双营西路66号院北京风景何营村中街16号",
          "洗浴中心",
          "韩式汗蒸馆(昌崔路)"
        ],
        [
          "北京市昌平区南邵镇双营西路66号院北京风景何营村中街16号",
          "便利店",
          "和乐美超市"
        ],
        [
          "北京市昌平区南邵镇双营西路66号院北京风景何营村中街16号",
          "理发店",
          "冬冬理发店(昌崔路)"
        ]
      ],
      "黑龙江省哈尔滨市道里区尚志街道麦凯乐国际公寓麦凯乐(哈尔滨总店)石头道街109号": [
        [
          "黑龙江省哈尔滨市道里区尚志街道麦凯乐国际公寓麦凯乐(哈尔滨总店)石头道街109号",
          "培训机构",
          "德福(华燕奥特莱斯购物中心)"
        ],
        [
          "黑龙江省哈尔滨市道里区尚志街道麦凯乐国际公寓麦凯乐(哈尔滨总店)石头道街109号",
          "幼儿园",
          "哈尔滨市政府机关第三幼儿园"
        ],
        [
          "黑龙江省哈尔滨市道里区尚志街道麦凯乐国际公寓麦凯乐(哈尔滨总店)石头道街109号",
          "银行",
          "哈尔滨农商银行(尚志大街)"
        ],
        [
          "黑龙江省哈尔滨市道里区尚志街道麦凯乐国际公寓麦凯乐(哈尔滨总店)石头道街109号",
          "住宅区",
          "公园一品"
        ],
        [
          "黑龙江省哈尔滨市道里区尚志街道麦凯乐国际公寓麦凯乐(哈尔滨总店)石头道街109号",
          "药店",
          "海晖医药(果园店)"
        ],
        [
          "黑龙江省哈尔滨市道里区尚志街道麦凯乐国际公寓麦凯乐(哈尔滨总店)石头道街109号",
          "医院",
          "兆麟社区卫生服务中心预防接种门诊"
        ],
        [
          "黑龙江省哈尔滨市道里区尚志街道麦凯乐国际公寓麦凯乐(哈尔滨总店)石头道街109号",
          "公交站",
          "中国人寿保险公司(道里七道街)(临时)(公交站)"
        ]
      ]
    },
    "NewAdd": [
      [
        "豫南风味小吃(昌崔路)",
        "便利店",
        "和乐美超市"
      ],
      [
        "和乐美超市",
        "餐厅",
        "豫南风味小吃(昌崔路)"
      ],
      [
        "博济堂门诊",
        "住宅区",
        "双营西路68号院"
      ],
      [
        "双营西路68号院",
        "医院",
        "博济堂门诊"
      ],
      [
        "哈尔滨农商银行(尚志大街)",
        "公交站",
        "中国人寿保险公司(道里七道街)(临时)(公交站)"
      ],
      [
        "中国人寿保险公司(道里七道街)(临时)(公交站)",
        "银行",
        "哈尔滨农商银行(尚志大街)"
      ],
      [
        "海晖医药(果园店)",
        "医院",
        "兆麟社区卫生服务中心预防接种门诊"
      ],
      [
        "兆麟社区卫生服务中心预防接种门诊",
        "药店",
        "海晖医药(果园店)"
      ]
    ]
  },
  "entity_description": {
    "User": 767,
    "PersonEntity": {
      "北京快乐茄信息技术有限公司": {
        "id": "2403551",
        "loc": [
          "116.314645303726",
          "40.0422684721658"
        ],
        "type": "公司"
      },
      "西安国际商务进修学院心理学院": {
        "id": "49631566",
        "loc": [
          "108.957246624517",
          "34.2288763631009"
        ],
        "type": "大学"
      },
      "北京市昌平区南邵镇双营西路66号院北京风景何营村中街16号": {
        "id": "2184488",
        "loc": [
          "116.298364676829",
          "40.2229518104727"
        ],
        "type": "住宅区"
      },
      "黑龙江省哈尔滨市道里区尚志街道麦凯乐国际公寓麦凯乐(哈尔滨总店)石头道街109号": {
        "id": "21392177",
        "loc": [
          "126.631359851696",
          "45.7775234215635"
        ],
        "type": "住宅区"
      }
    },
    "OneStepEntity": {
      "百佳利社区便民超市": {
        "id": "2841285",
        "loc": [
          "116.305504",
          "40.035631"
        ],
        "type": "便利店"
      },
      "首钢餐饮第72商亭": {
        "id": "2841297",
        "loc": [
          "116.30972",
          "40.03389"
        ],
        "type": "超市"
      },
      "聚瑞祥美国加州牛肉面大王(上地科实大厦店)": {
        "id": "2612646",
        "loc": [
          "116.311997",
          "40.034291"
        ],
        "type": "餐厅"
      },
      "老实人饺子馆": {
        "id": "48785809",
        "loc": [
          "108.954151",
          "34.225666"
        ],
        "type": "餐厅"
      },
      "乐游网咖": {
        "id": "48784842",
        "loc": [
          "108.953096",
          "34.222986"
        ],
        "type": "网吧"
      },
      "百利甜蛋糕": {
        "id": "48785315",
        "loc": [
          "108.952044",
          "34.222342"
        ],
        "type": "蛋糕店"
      },
      "床上用品棉被窗帘": {
        "id": "2825694",
        "loc": [
          "116.290346",
          "40.212604"
        ],
        "type": "家居建材市场"
      },
      "豫南风味小吃(昌崔路)": {
        "id": "2595629",
        "loc": [
          "116.295123",
          "40.220471"
        ],
        "type": "餐厅"
      },
      "博济堂门诊": {
        "id": "3508102",
        "loc": [
          "116.292335",
          "40.212562"
        ],
        "type": "医院"
      },
      "何营(公交站)": {
        "id": "3379700",
        "loc": [
          "116.288094",
          "40.219284"
        ],
        "type": "公交站"
      },
      "双营西路68号院": {
        "id": "3308336",
        "loc": [
          "116.292268",
          "40.214125"
        ],
        "type": "住宅区"
      },
      "韩式汗蒸馆(昌崔路)": {
        "id": "3144440",
        "loc": [
          "116.292708",
          "40.219855"
        ],
        "type": "洗浴中心"
      },
      "和乐美超市": {
        "id": "2825888",
        "loc": [
          "116.295044",
          "40.220458"
        ],
        "type": "便利店"
      },
      "冬冬理发店(昌崔路)": {
        "id": "3144448",
        "loc": [
          "116.289482",
          "40.219716"
        ],
        "type": "理发店"
      },
      "德福(华燕奥特莱斯购物中心)": {
        "id": "21375396",
        "loc": [
          "126.628831",
          "45.770358"
        ],
        "type": "培训机构"
      },
      "哈尔滨市政府机关第三幼儿园": {
        "id": "21392175",
        "loc": [
          "126.625551",
          "45.771845"
        ],
        "type": "幼儿园"
      },
      "哈尔滨农商银行(尚志大街)": {
        "id": "21314898",
        "loc": [
          "126.622658",
          "45.773521"
        ],
        "type": "银行"
      },
      "公园一品": {
        "id": "21314862",
        "loc": [
          "126.62435",
          "45.775284"
        ],
        "type": "住宅区"
      },
      "海晖医药(果园店)": {
        "id": "21480825",
        "loc": [
          "126.629144",
          "45.773976"
        ],
        "type": "药店"
      },
      "兆麟社区卫生服务中心预防接种门诊": {
        "id": "21480842",
        "loc": [
          "126.629885",
          "45.77337"
        ],
        "type": "医院"
      },
      "中国人寿保险公司(道里七道街)(临时)(公交站)": {
        "id": "21363372",
        "loc": [
          "126.622902",
          "45.77227"
        ],
        "type": "公交站"
      }
    }
  }
}