{
  "“北京海良永昌市政工程有限公司” “尚选便利店”": "0",
  "“北京海良永昌市政工程有限公司” “明军康寿大药房”": "6",
  "“北京海良永昌市政工程有限公司” “2008年”": "12",
  "“河北科技大学” “靓影美甲屋”": "3",
  "“河北科技大学” “河北科技大学乒乓球运动场地”": "82",
  "“北京海良永昌市政工程有限公司” “富迪平价超市(贾后疃村店)”": "2",
  "“河北科技大学” “巴西烤肉饭”": "1",
  "“河北科技大学” “河北科技大学-河北省书画院”": "3,160",
  "“河北科技大学” “孙鹤旭”": "22,600",
  "“河北科技大学” “兴业，尽责”": "3,240",
  "“河北省石家庄市裕华区裕华路街道石家庄河北科技大学招待所裕华东路72号” “麦芝鲜(范西路店)”": "4,760",
  "“河北省石家庄市裕华区裕华路街道石家庄河北科技大学招待所裕华东路72号” “OPPO(范西路)”": "7,580",
  "“河北省石家庄市裕华区裕华路街道石家庄河北科技大学招待所裕华东路72号” “腾皓开心炒坊”": "15",
  "“河北科技大学” “石家庄”": "56,200",
  "“河北科技大学” “韩布兴”": "68",
  "“河北省石家庄市裕华区裕华路街道石家庄河北科技大学招待所裕华东路72号” “沫沫工坊”": "11,200",
  "“河北省石家庄市裕华区裕华路街道石家庄河北科技大学招待所裕华东路72号” “花知语花艺”": "25,000",
  "“河北省石家庄市裕华区裕华路街道石家庄河北科技大学招待所裕华东路72号” “国大365便利店(设计院新店)”": "23,400",
  "“河北省石家庄市裕华区裕华路街道石家庄河北科技大学招待所裕华东路72号” “A.R.T Furniture”": "5,060",
  "“河北省石家庄市裕华区裕华路街道石家庄河北科技大学招待所裕华东路72号” “河北科技大学富强大街小区”": "5,920",
  "“河北科技大学” “1956年”": "3,810",
  "“河北省石家庄市裕华区裕华路街道石家庄河北科技大学招待所裕华东路72号” “锦绣建筑书店”": "20,700",
  "“富迪平价超市(贾后疃村店)” “明军康寿大药房”": "7",
  "“沫沫工坊” “麦芝鲜(范西路店)”": "0",
  "“沫沫工坊” “OPPO(范西路)”": "2",
  "“麦芝鲜(范西路店)” “OPPO(范西路)”": "5",
  "“腾皓开心炒坊” “神州七星酒店”": "1",
  "“锦绣建筑书店” “A.R.T Furniture”": "0",
  "“河北省石家庄市裕华区裕华路街道石家庄河北科技大学招待所裕华东路72号” “神州七星酒店”": "11,400",
  "“腾皓开心炒坊” “花知语花艺”": "0"
}