{
  "“张家港天润针织有限公司” “上正威克多羽毛球馆”": "0",
  "“张家港天润针织有限公司” “大排挡夜宵”": "0",
  "“张家港天润针织有限公司” “大新田园酒店”": "0",
  "“张家港天润针织有限公司” “8090时尚造型(悦丰新村北区东)”": "9",
  "“张家港天润针织有限公司” “紫藤苑足浴”": "0",
  "“张家港天润针织有限公司” “中国移动移动便利店”": "0",
  "“张家港天润针织有限公司” “大新利群农民专业合作社”": "0",
  "“张家港天润针织有限公司” “安卓智能手机大卖场”": "0",
  "“成都信息工程大学航空港校区大气科学学院” “超越时尚形象设计店(黄河北路店)”": "94",
  "“成都信息工程大学航空港校区大气科学学院” “家家福超市(学府路分店)”": "100",
  "“成都信息工程大学航空港校区大气科学学院” “成都信息工程大学航空港校区图书馆”": "1,820",
  "“成都信息工程大学航空港校区大气科学学院” “知音门诊”": "1",
  "“成都信息工程大学航空港校区大气科学学院” “家常味(学府路二段)”": "605",
  "“成都信息工程大学航空港校区大气科学学院” “华亿连锁超市(黄河北路店)”": "10",
  "“成都信息工程大学航空港校区大气科学学院” “近藤花艺(百合鲜花)”": "4",
  "“北京市海淀区清河街道阳光北里小营西路12号” “粉丝粉条”": "6",
  "“北京市海淀区清河街道阳光北里小营西路12号” “轩哥的元素”": "21",
  "“北京市海淀区清河街道阳光北里小营西路12号” “利奥跆拳道”": "0",
  "“北京市海淀区清河街道阳光北里小营西路12号” “北京普泽康大药房”": "28",
  "“北京市海淀区清河街道阳光北里小营西路12号” “鑫开日用百货店”": "0",
  "“北京市海淀区清河街道阳光北里小营西路12号” “7天酒店(西小口地铁站店)”": "1,570",
  "“北京市海淀区清河街道阳光北里小营西路12号” “东方丽人美甲(安宁庄东路店)”": "38",
  "“8090时尚造型(悦丰新村北区东)” “安卓智能手机大卖场”": "0",
  "“中国移动移动便利店” “大新利群农民专业合作社”": "3",
  "“成都信息工程大学航空港校区大气科学学院” “岳氏盲人理疗按摩”": "0",
  "“超越时尚形象设计店(黄河北路店)” “家家福超市(学府路分店)”": "2",
  "“超越时尚形象设计店(黄河北路店)” “华亿连锁超市(黄河北路店)”": "32",
  "“超越时尚形象设计店(黄河北路店)” “近藤花艺(百合鲜花)”": "9",
  "“超越时尚形象设计店(黄河北路店)” “岳氏盲人理疗按摩”": "0",
  "“家家福超市(学府路分店)” “华亿连锁超市(黄河北路店)”": "812",
  "“家家福超市(学府路分店)” “近藤花艺(百合鲜花)”": "0",
  "“家家福超市(学府路分店)” “岳氏盲人理疗按摩”": "14",
  "“华亿连锁超市(黄河北路店)” “近藤花艺(百合鲜花)”": "5",
  "“华亿连锁超市(黄河北路店)” “岳氏盲人理疗按摩”": "14",
  "“粉丝粉条” “轩哥的元素”": "209",
  "“张家港天润针织有限公司” “悦丰新村北区”": "0",
  "“近藤花艺(百合鲜花)” “岳氏盲人理疗按摩”": "0"
}