{
  "nodes": [
    "完美世界",
    "北京外国语大学",
    "北京市大兴区北京经济技术开发区新康家园(燕景佳园东南)新康家园文化园西路26号",
    "重庆市万州区周家坝街道重庆市万州第一人民医院万州区第四人民医院职工宿舍天城东路388号",
    "7-ELEVEn(上丁软件园店)",
    "一号雪茄吧",
    "姜记麻辣烫",
    "宫廷名糕点(华南店)",
    "手佳推拿馆",
    "洁净干洗店(痴树花路)",
    "纤秀美容养生馆(华南路店)",
    "上海炒货居(丹阳分店)",
    "徐氏粮油烟酒",
    "依恋花屋",
    "1941年",
    "合肥",
    "彭龙",
    "傅莹",
    "兼容并蓄 博学笃行",
    "百旺居",
    "北京稻香村(华冠亦庄店)",
    "元味串串香",
    "琪莱宾馆",
    "威英副食店",
    "海利不锈钢管",
    "飘雪音响",
    "流水社区",
    "重庆三峡银行(天城支行)",
    "黑子水果超市",
    "丽雅美容养身馆"
  ],
  "personal_nodes": [
    0,
    1,
    2,
    3
  ],
  "personal_information": {
    "company": 0,
    "university": 1,
    "live_in": 2,
    "born_in": 3
  },
  "node2idx": {
    "完美世界": 0,
    "北京外国语大学": 1,
    "北京市大兴区北京经济技术开发区新康家园(燕景佳园东南)新康家园文化园西路26号": 2,
    "重庆市万州区周家坝街道重庆市万州第一人民医院万州区第四人民医院职工宿舍天城东路388号": 3,
    "7-ELEVEn(上丁软件园店)": 4,
    "一号雪茄吧": 5,
    "姜记麻辣烫": 6,
    "宫廷名糕点(华南店)": 7,
    "手佳推拿馆": 8,
    "洁净干洗店(痴树花路)": 9,
    "纤秀美容养生馆(华南路店)": 10,
    "上海炒货居(丹阳分店)": 11,
    "徐氏粮油烟酒": 12,
    "依恋花屋": 13,
    "1941年": 14,
    "合肥": 15,
    "彭龙": 16,
    "傅莹": 17,
    "兼容并蓄 博学笃行": 18,
    "百旺居": 19,
    "北京稻香村(华冠亦庄店)": 20,
    "元味串串香": 21,
    "琪莱宾馆": 22,
    "威英副食店": 23,
    "海利不锈钢管": 24,
    "飘雪音响": 25,
    "流水社区": 26,
    "重庆三峡银行(天城支行)": 27,
    "黑子水果超市": 28,
    "丽雅美容养身馆": 29
  },
  "idx2node": {
    "0": "完美世界",
    "1": "北京外国语大学",
    "2": "北京市大兴区北京经济技术开发区新康家园(燕景佳园东南)新康家园文化园西路26号",
    "3": "重庆市万州区周家坝街道重庆市万州第一人民医院万州区第四人民医院职工宿舍天城东路388号",
    "4": "7-ELEVEn(上丁软件园店)",
    "5": "一号雪茄吧",
    "6": "姜记麻辣烫",
    "7": "宫廷名糕点(华南店)",
    "8": "手佳推拿馆",
    "9": "洁净干洗店(痴树花路)",
    "10": "纤秀美容养生馆(华南路店)",
    "11": "上海炒货居(丹阳分店)",
    "12": "徐氏粮油烟酒",
    "13": "依恋花屋",
    "14": "1941年",
    "15": "合肥",
    "16": "彭龙",
    "17": "傅莹",
    "18": "兼容并蓄 博学笃行",
    "19": "百旺居",
    "20": "北京稻香村(华冠亦庄店)",
    "21": "元味串串香",
    "22": "琪莱宾馆",
    "23": "威英副食店",
    "24": "海利不锈钢管",
    "25": "飘雪音响",
    "26": "流水社区",
    "27": "重庆三峡银行(天城支行)",
    "28": "黑子水果超市",
    "29": "丽雅美容养身馆"
  },
  "edges": [
    [
      "7-ELEVEn(上丁软件园店)",
      "超市",
      "完美世界"
    ],
    [
      "一号雪茄吧",
      "餐厅",
      "完美世界"
    ],
    [
      "姜记麻辣烫",
      "餐厅",
      "北京外国语大学"
    ],
    [
      "宫廷名糕点(华南店)",
      "蛋糕店",
      "北京外国语大学"
    ],
    [
      "手佳推拿馆",
      "洗浴中心",
      "北京外国语大学"
    ],
    [
      "洁净干洗店(痴树花路)",
      "洗衣店",
      "北京外国语大学"
    ],
    [
      "纤秀美容养生馆(华南路店)",
      "理发店",
      "北京外国语大学"
    ],
    [
      "上海炒货居(丹阳分店)",
      "果蔬店",
      "北京外国语大学"
    ],
    [
      "徐氏粮油烟酒",
      "便利店",
      "北京外国语大学"
    ],
    [
      "依恋花屋",
      "花鸟鱼虫市场",
      "北京外国语大学"
    ],
    [
      "1941年",
      "成立时间",
      "北京外国语大学"
    ],
    [
      "合肥",
      "所属地区",
      "北京外国语大学"
    ],
    [
      "彭龙",
      "校长",
      "北京外国语大学"
    ],
    [
      "傅莹",
      "知名校友",
      "北京外国语大学"
    ],
    [
      "兼容并蓄 博学笃行",
      "校训",
      "北京外国语大学"
    ],
    [
      "百旺居",
      "餐厅",
      "北京市大兴区北京经济技术开发区新康家园(燕景佳园东南)新康家园文化园西路26号"
    ],
    [
      "北京稻香村(华冠亦庄店)",
      "蛋糕店",
      "北京市大兴区北京经济技术开发区新康家园(燕景佳园东南)新康家园文化园西路26号"
    ],
    [
      "元味串串香",
      "餐厅",
      "重庆市万州区周家坝街道重庆市万州第一人民医院万州区第四人民医院职工宿舍天城东路388号"
    ],
    [
      "琪莱宾馆",
      "宾馆酒店",
      "重庆市万州区周家坝街道重庆市万州第一人民医院万州区第四人民医院职工宿舍天城东路388号"
    ],
    [
      "威英副食店",
      "便利店",
      "重庆市万州区周家坝街道重庆市万州第一人民医院万州区第四人民医院职工宿舍天城东路388号"
    ],
    [
      "海利不锈钢管",
      "商场",
      "重庆市万州区周家坝街道重庆市万州第一人民医院万州区第四人民医院职工宿舍天城东路388号"
    ],
    [
      "飘雪音响",
      "数码商城",
      "重庆市万州区周家坝街道重庆市万州第一人民医院万州区第四人民医院职工宿舍天城东路388号"
    ],
    [
      "流水社区",
      "住宅区",
      "重庆市万州区周家坝街道重庆市万州第一人民医院万州区第四人民医院职工宿舍天城东路388号"
    ],
    [
      "重庆三峡银行(天城支行)",
      "银行",
      "重庆市万州区周家坝街道重庆市万州第一人民医院万州区第四人民医院职工宿舍天城东路388号"
    ],
    [
      "黑子水果超市",
      "果蔬店",
      "重庆市万州区周家坝街道重庆市万州第一人民医院万州区第四人民医院职工宿舍天城东路388号"
    ],
    [
      "丽雅美容养身馆",
      "理发店",
      "重庆市万州区周家坝街道重庆市万州第一人民医院万州区第四人民医院职工宿舍天城东路388号"
    ],
    [
      "宫廷名糕点(华南店)",
      "蛋糕店",
      "姜记麻辣烫"
    ],
    [
      "姜记麻辣烫",
      "餐厅",
      "宫廷名糕点(华南店)"
    ],
    [
      "纤秀美容养生馆(华南路店)",
      "理发店",
      "姜记麻辣烫"
    ],
    [
      "姜记麻辣烫",
      "餐厅",
      "纤秀美容养生馆(华南路店)"
    ],
    [
      "上海炒货居(丹阳分店)",
      "果蔬店",
      "姜记麻辣烫"
    ],
    [
      "姜记麻辣烫",
      "餐厅",
      "上海炒货居(丹阳分店)"
    ],
    [
      "徐氏粮油烟酒",
      "便利店",
      "姜记麻辣烫"
    ],
    [
      "姜记麻辣烫",
      "餐厅",
      "徐氏粮油烟酒"
    ],
    [
      "依恋花屋",
      "花鸟鱼虫市场",
      "姜记麻辣烫"
    ],
    [
      "姜记麻辣烫",
      "餐厅",
      "依恋花屋"
    ],
    [
      "纤秀美容养生馆(华南路店)",
      "理发店",
      "宫廷名糕点(华南店)"
    ],
    [
      "宫廷名糕点(华南店)",
      "蛋糕店",
      "纤秀美容养生馆(华南路店)"
    ],
    [
      "上海炒货居(丹阳分店)",
      "果蔬店",
      "宫廷名糕点(华南店)"
    ],
    [
      "宫廷名糕点(华南店)",
      "蛋糕店",
      "上海炒货居(丹阳分店)"
    ],
    [
      "徐氏粮油烟酒",
      "便利店",
      "宫廷名糕点(华南店)"
    ],
    [
      "宫廷名糕点(华南店)",
      "蛋糕店",
      "徐氏粮油烟酒"
    ],
    [
      "依恋花屋",
      "花鸟鱼虫市场",
      "宫廷名糕点(华南店)"
    ],
    [
      "宫廷名糕点(华南店)",
      "蛋糕店",
      "依恋花屋"
    ],
    [
      "依恋花屋",
      "花鸟鱼虫市场",
      "手佳推拿馆"
    ],
    [
      "手佳推拿馆",
      "洗浴中心",
      "依恋花屋"
    ],
    [
      "上海炒货居(丹阳分店)",
      "果蔬店",
      "纤秀美容养生馆(华南路店)"
    ],
    [
      "纤秀美容养生馆(华南路店)",
      "理发店",
      "上海炒货居(丹阳分店)"
    ],
    [
      "徐氏粮油烟酒",
      "便利店",
      "纤秀美容养生馆(华南路店)"
    ],
    [
      "纤秀美容养生馆(华南路店)",
      "理发店",
      "徐氏粮油烟酒"
    ],
    [
      "徐氏粮油烟酒",
      "便利店",
      "上海炒货居(丹阳分店)"
    ],
    [
      "上海炒货居(丹阳分店)",
      "果蔬店",
      "徐氏粮油烟酒"
    ],
    [
      "依恋花屋",
      "花鸟鱼虫市场",
      "徐氏粮油烟酒"
    ],
    [
      "徐氏粮油烟酒",
      "便利店",
      "依恋花屋"
    ],
    [
      "海利不锈钢管",
      "商场",
      "元味串串香"
    ],
    [
      "元味串串香",
      "餐厅",
      "海利不锈钢管"
    ],
    [
      "流水社区",
      "住宅区",
      "元味串串香"
    ],
    [
      "元味串串香",
      "餐厅",
      "流水社区"
    ],
    [
      "黑子水果超市",
      "果蔬店",
      "元味串串香"
    ],
    [
      "元味串串香",
      "餐厅",
      "黑子水果超市"
    ],
    [
      "丽雅美容养身馆",
      "理发店",
      "元味串串香"
    ],
    [
      "元味串串香",
      "餐厅",
      "丽雅美容养身馆"
    ],
    [
      "威英副食店",
      "便利店",
      "琪莱宾馆"
    ],
    [
      "琪莱宾馆",
      "宾馆酒店",
      "威英副食店"
    ],
    [
      "飘雪音响",
      "数码商城",
      "琪莱宾馆"
    ],
    [
      "琪莱宾馆",
      "宾馆酒店",
      "飘雪音响"
    ],
    [
      "丽雅美容养身馆",
      "理发店",
      "琪莱宾馆"
    ],
    [
      "琪莱宾馆",
      "宾馆酒店",
      "丽雅美容养身馆"
    ],
    [
      "飘雪音响",
      "数码商城",
      "威英副食店"
    ],
    [
      "威英副食店",
      "便利店",
      "飘雪音响"
    ],
    [
      "丽雅美容养身馆",
      "理发店",
      "威英副食店"
    ],
    [
      "威英副食店",
      "便利店",
      "丽雅美容养身馆"
    ],
    [
      "流水社区",
      "住宅区",
      "海利不锈钢管"
    ],
    [
      "海利不锈钢管",
      "商场",
      "流水社区"
    ],
    [
      "黑子水果超市",
      "果蔬店",
      "海利不锈钢管"
    ],
    [
      "海利不锈钢管",
      "商场",
      "黑子水果超市"
    ],
    [
      "丽雅美容养身馆",
      "理发店",
      "飘雪音响"
    ],
    [
      "飘雪音响",
      "数码商城",
      "丽雅美容养身馆"
    ],
    [
      "黑子水果超市",
      "果蔬店",
      "流水社区"
    ],
    [
      "流水社区",
      "住宅区",
      "黑子水果超市"
    ],
    [
      "丽雅美容养身馆",
      "理发店",
      "黑子水果超市"
    ],
    [
      "黑子水果超市",
      "果蔬店",
      "丽雅美容养身馆"
    ]
  ],
  "edge_se_freqs": [
    19,
    0,
    61,
    1440,
    3,
    0,
    71,
    65,
    751,
    11500,
    23000,
    2100000,
    21100,
    85,
    4920,
    2000,
    2000,
    6510,
    6510,
    6510,
    6510,
    6510,
    17800,
    6720,
    6580,
    6510,
    70,
    70,
    0,
    0,
    0,
    0,
    0,
    0,
    0,
    0,
    210000,
    210000,
    96,
    96,
    56,
    56,
    43800,
    43800,
    0,
    0,
    3,
    3,
    0,
    0,
    65,
    65,
    607,
    607,
    0,
    0,
    0,
    0,
    0,
    0,
    0,
    0,
    29,
    29,
    73,
    73,
    0,
    0,
    0,
    0,
    0,
    0,
    0,
    0,
    0,
    0,
    0,
    0,
    22,
    22,
    0,
    0
  ],
  "one_step_nodes": {
    "完美世界": [
      "7-ELEVEn(上丁软件园店)",
      "一号雪茄吧"
    ],
    "北京外国语大学": [
      "姜记麻辣烫",
      "宫廷名糕点(华南店)",
      "手佳推拿馆",
      "洁净干洗店(痴树花路)",
      "纤秀美容养生馆(华南路店)",
      "上海炒货居(丹阳分店)",
      "徐氏粮油烟酒",
      "依恋花屋",
      "1941年",
      "合肥",
      "彭龙",
      "傅莹",
      "兼容并蓄 博学笃行"
    ],
    "北京市大兴区北京经济技术开发区新康家园(燕景佳园东南)新康家园文化园西路26号": [
      "百旺居",
      "北京稻香村(华冠亦庄店)"
    ],
    "重庆市万州区周家坝街道重庆市万州第一人民医院万州区第四人民医院职工宿舍天城东路388号": [
      "元味串串香",
      "琪莱宾馆",
      "威英副食店",
      "海利不锈钢管",
      "飘雪音响",
      "流水社区",
      "重庆三峡银行(天城支行)",
      "黑子水果超市",
      "丽雅美容养身馆"
    ]
  },
  "node_edges": {
    "完美世界": [
      [
        "7-ELEVEn(上丁软件园店)",
        "超市",
        "完美世界"
      ],
      [
        "一号雪茄吧",
        "餐厅",
        "完美世界"
      ]
    ],
    "北京外国语大学": [
      [
        "姜记麻辣烫",
        "餐厅",
        "北京外国语大学"
      ],
      [
        "宫廷名糕点(华南店)",
        "蛋糕店",
        "北京外国语大学"
      ],
      [
        "手佳推拿馆",
        "洗浴中心",
        "北京外国语大学"
      ],
      [
        "洁净干洗店(痴树花路)",
        "洗衣店",
        "北京外国语大学"
      ],
      [
        "纤秀美容养生馆(华南路店)",
        "理发店",
        "北京外国语大学"
      ],
      [
        "上海炒货居(丹阳分店)",
        "果蔬店",
        "北京外国语大学"
      ],
      [
        "徐氏粮油烟酒",
        "便利店",
        "北京外国语大学"
      ],
      [
        "依恋花屋",
        "花鸟鱼虫市场",
        "北京外国语大学"
      ],
      [
        "1941年",
        "成立时间",
        "北京外国语大学"
      ],
      [
        "合肥",
        "所属地区",
        "北京外国语大学"
      ],
      [
        "彭龙",
        "校长",
        "北京外国语大学"
      ],
      [
        "傅莹",
        "知名校友",
        "北京外国语大学"
      ],
      [
        "兼容并蓄 博学笃行",
        "校训",
        "北京外国语大学"
      ]
    ],
    "北京市大兴区北京经济技术开发区新康家园(燕景佳园东南)新康家园文化园西路26号": [
      [
        "百旺居",
        "餐厅",
        "北京市大兴区北京经济技术开发区新康家园(燕景佳园东南)新康家园文化园西路26号"
      ],
      [
        "北京稻香村(华冠亦庄店)",
        "蛋糕店",
        "北京市大兴区北京经济技术开发区新康家园(燕景佳园东南)新康家园文化园西路26号"
      ]
    ],
    "重庆市万州区周家坝街道重庆市万州第一人民医院万州区第四人民医院职工宿舍天城东路388号": [
      [
        "元味串串香",
        "餐厅",
        "重庆市万州区周家坝街道重庆市万州第一人民医院万州区第四人民医院职工宿舍天城东路388号"
      ],
      [
        "琪莱宾馆",
        "宾馆酒店",
        "重庆市万州区周家坝街道重庆市万州第一人民医院万州区第四人民医院职工宿舍天城东路388号"
      ],
      [
        "威英副食店",
        "便利店",
        "重庆市万州区周家坝街道重庆市万州第一人民医院万州区第四人民医院职工宿舍天城东路388号"
      ],
      [
        "海利不锈钢管",
        "商场",
        "重庆市万州区周家坝街道重庆市万州第一人民医院万州区第四人民医院职工宿舍天城东路388号"
      ],
      [
        "飘雪音响",
        "数码商城",
        "重庆市万州区周家坝街道重庆市万州第一人民医院万州区第四人民医院职工宿舍天城东路388号"
      ],
      [
        "流水社区",
        "住宅区",
        "重庆市万州区周家坝街道重庆市万州第一人民医院万州区第四人民医院职工宿舍天城东路388号"
      ],
      [
        "重庆三峡银行(天城支行)",
        "银行",
        "重庆市万州区周家坝街道重庆市万州第一人民医院万州区第四人民医院职工宿舍天城东路388号"
      ],
      [
        "黑子水果超市",
        "果蔬店",
        "重庆市万州区周家坝街道重庆市万州第一人民医院万州区第四人民医院职工宿舍天城东路388号"
      ],
      [
        "丽雅美容养身馆",
        "理发店",
        "重庆市万州区周家坝街道重庆市万州第一人民医院万州区第四人民医院职工宿舍天城东路388号"
      ]
    ],
    "7-ELEVEn(上丁软件园店)": [],
    "一号雪茄吧": [],
    "姜记麻辣烫": [
      [
        "宫廷名糕点(华南店)",
        "蛋糕店",
        "姜记麻辣烫"
      ],
      [
        "纤秀美容养生馆(华南路店)",
        "理发店",
        "姜记麻辣烫"
      ],
      [
        "上海炒货居(丹阳分店)",
        "果蔬店",
        "姜记麻辣烫"
      ],
      [
        "徐氏粮油烟酒",
        "便利店",
        "姜记麻辣烫"
      ],
      [
        "依恋花屋",
        "花鸟鱼虫市场",
        "姜记麻辣烫"
      ]
    ],
    "宫廷名糕点(华南店)": [
      [
        "姜记麻辣烫",
        "餐厅",
        "宫廷名糕点(华南店)"
      ],
      [
        "纤秀美容养生馆(华南路店)",
        "理发店",
        "宫廷名糕点(华南店)"
      ],
      [
        "上海炒货居(丹阳分店)",
        "果蔬店",
        "宫廷名糕点(华南店)"
      ],
      [
        "徐氏粮油烟酒",
        "便利店",
        "宫廷名糕点(华南店)"
      ],
      [
        "依恋花屋",
        "花鸟鱼虫市场",
        "宫廷名糕点(华南店)"
      ]
    ],
    "手佳推拿馆": [
      [
        "依恋花屋",
        "花鸟鱼虫市场",
        "手佳推拿馆"
      ]
    ],
    "洁净干洗店(痴树花路)": [],
    "纤秀美容养生馆(华南路店)": [
      [
        "姜记麻辣烫",
        "餐厅",
        "纤秀美容养生馆(华南路店)"
      ],
      [
        "宫廷名糕点(华南店)",
        "蛋糕店",
        "纤秀美容养生馆(华南路店)"
      ],
      [
        "上海炒货居(丹阳分店)",
        "果蔬店",
        "纤秀美容养生馆(华南路店)"
      ],
      [
        "徐氏粮油烟酒",
        "便利店",
        "纤秀美容养生馆(华南路店)"
      ]
    ],
    "上海炒货居(丹阳分店)": [
      [
        "姜记麻辣烫",
        "餐厅",
        "上海炒货居(丹阳分店)"
      ],
      [
        "宫廷名糕点(华南店)",
        "蛋糕店",
        "上海炒货居(丹阳分店)"
      ],
      [
        "纤秀美容养生馆(华南路店)",
        "理发店",
        "上海炒货居(丹阳分店)"
      ],
      [
        "徐氏粮油烟酒",
        "便利店",
        "上海炒货居(丹阳分店)"
      ]
    ],
    "徐氏粮油烟酒": [
      [
        "姜记麻辣烫",
        "餐厅",
        "徐氏粮油烟酒"
      ],
      [
        "宫廷名糕点(华南店)",
        "蛋糕店",
        "徐氏粮油烟酒"
      ],
      [
        "纤秀美容养生馆(华南路店)",
        "理发店",
        "徐氏粮油烟酒"
      ],
      [
        "上海炒货居(丹阳分店)",
        "果蔬店",
        "徐氏粮油烟酒"
      ],
      [
        "依恋花屋",
        "花鸟鱼虫市场",
        "徐氏粮油烟酒"
      ]
    ],
    "依恋花屋": [
      [
        "姜记麻辣烫",
        "餐厅",
        "依恋花屋"
      ],
      [
        "宫廷名糕点(华南店)",
        "蛋糕店",
        "依恋花屋"
      ],
      [
        "手佳推拿馆",
        "洗浴中心",
        "依恋花屋"
      ],
      [
        "徐氏粮油烟酒",
        "便利店",
        "依恋花屋"
      ]
    ],
    "1941年": [],
    "合肥": [],
    "彭龙": [],
    "傅莹": [],
    "兼容并蓄 博学笃行": [],
    "百旺居": [],
    "北京稻香村(华冠亦庄店)": [],
    "元味串串香": [
      [
        "海利不锈钢管",
        "商场",
        "元味串串香"
      ],
      [
        "流水社区",
        "住宅区",
        "元味串串香"
      ],
      [
        "黑子水果超市",
        "果蔬店",
        "元味串串香"
      ],
      [
        "丽雅美容养身馆",
        "理发店",
        "元味串串香"
      ]
    ],
    "琪莱宾馆": [
      [
        "威英副食店",
        "便利店",
        "琪莱宾馆"
      ],
      [
        "飘雪音响",
        "数码商城",
        "琪莱宾馆"
      ],
      [
        "丽雅美容养身馆",
        "理发店",
        "琪莱宾馆"
      ]
    ],
    "威英副食店": [
      [
        "琪莱宾馆",
        "宾馆酒店",
        "威英副食店"
      ],
      [
        "飘雪音响",
        "数码商城",
        "威英副食店"
      ],
      [
        "丽雅美容养身馆",
        "理发店",
        "威英副食店"
      ]
    ],
    "海利不锈钢管": [
      [
        "元味串串香",
        "餐厅",
        "海利不锈钢管"
      ],
      [
        "流水社区",
        "住宅区",
        "海利不锈钢管"
      ],
      [
        "黑子水果超市",
        "果蔬店",
        "海利不锈钢管"
      ]
    ],
    "飘雪音响": [
      [
        "琪莱宾馆",
        "宾馆酒店",
        "飘雪音响"
      ],
      [
        "威英副食店",
        "便利店",
        "飘雪音响"
      ],
      [
        "丽雅美容养身馆",
        "理发店",
        "飘雪音响"
      ]
    ],
    "流水社区": [
      [
        "元味串串香",
        "餐厅",
        "流水社区"
      ],
      [
        "海利不锈钢管",
        "商场",
        "流水社区"
      ],
      [
        "黑子水果超市",
        "果蔬店",
        "流水社区"
      ]
    ],
    "重庆三峡银行(天城支行)": [],
    "黑子水果超市": [
      [
        "元味串串香",
        "餐厅",
        "黑子水果超市"
      ],
      [
        "海利不锈钢管",
        "商场",
        "黑子水果超市"
      ],
      [
        "流水社区",
        "住宅区",
        "黑子水果超市"
      ],
      [
        "丽雅美容养身馆",
        "理发店",
        "黑子水果超市"
      ]
    ],
    "丽雅美容养身馆": [
      [
        "元味串串香",
        "餐厅",
        "丽雅美容养身馆"
      ],
      [
        "琪莱宾馆",
        "宾馆酒店",
        "丽雅美容养身馆"
      ],
      [
        "威英副食店",
        "便利店",
        "丽雅美容养身馆"
      ],
      [
        "飘雪音响",
        "数码商城",
        "丽雅美容养身馆"
      ],
      [
        "黑子水果超市",
        "果蔬店",
        "丽雅美容养身馆"
      ]
    ]
  },
  "one_step_node_edges": {
    "完美世界": [
      [
        "7-ELEVEn(上丁软件园店)",
        "超市",
        "完美世界"
      ],
      [
        "一号雪茄吧",
        "餐厅",
        "完美世界"
      ]
    ],
    "北京外国语大学": [
      [
        "姜记麻辣烫",
        "餐厅",
        "北京外国语大学"
      ],
      [
        "宫廷名糕点(华南店)",
        "蛋糕店",
        "北京外国语大学"
      ],
      [
        "手佳推拿馆",
        "洗浴中心",
        "北京外国语大学"
      ],
      [
        "洁净干洗店(痴树花路)",
        "洗衣店",
        "北京外国语大学"
      ],
      [
        "纤秀美容养生馆(华南路店)",
        "理发店",
        "北京外国语大学"
      ],
      [
        "上海炒货居(丹阳分店)",
        "果蔬店",
        "北京外国语大学"
      ],
      [
        "徐氏粮油烟酒",
        "便利店",
        "北京外国语大学"
      ],
      [
        "依恋花屋",
        "花鸟鱼虫市场",
        "北京外国语大学"
      ],
      [
        "1941年",
        "成立时间",
        "北京外国语大学"
      ],
      [
        "合肥",
        "所属地区",
        "北京外国语大学"
      ],
      [
        "彭龙",
        "校长",
        "北京外国语大学"
      ],
      [
        "傅莹",
        "知名校友",
        "北京外国语大学"
      ],
      [
        "兼容并蓄 博学笃行",
        "校训",
        "北京外国语大学"
      ],
      [
        "宫廷名糕点(华南店)",
        "蛋糕店",
        "姜记麻辣烫"
      ],
      [
        "姜记麻辣烫",
        "餐厅",
        "宫廷名糕点(华南店)"
      ],
      [
        "纤秀美容养生馆(华南路店)",
        "理发店",
        "姜记麻辣烫"
      ],
      [
        "姜记麻辣烫",
        "餐厅",
        "纤秀美容养生馆(华南路店)"
      ],
      [
        "上海炒货居(丹阳分店)",
        "果蔬店",
        "姜记麻辣烫"
      ],
      [
        "姜记麻辣烫",
        "餐厅",
        "上海炒货居(丹阳分店)"
      ],
      [
        "徐氏粮油烟酒",
        "便利店",
        "姜记麻辣烫"
      ],
      [
        "姜记麻辣烫",
        "餐厅",
        "徐氏粮油烟酒"
      ],
      [
        "依恋花屋",
        "花鸟鱼虫市场",
        "姜记麻辣烫"
      ],
      [
        "姜记麻辣烫",
        "餐厅",
        "依恋花屋"
      ],
      [
        "纤秀美容养生馆(华南路店)",
        "理发店",
        "宫廷名糕点(华南店)"
      ],
      [
        "宫廷名糕点(华南店)",
        "蛋糕店",
        "纤秀美容养生馆(华南路店)"
      ],
      [
        "上海炒货居(丹阳分店)",
        "果蔬店",
        "宫廷名糕点(华南店)"
      ],
      [
        "宫廷名糕点(华南店)",
        "蛋糕店",
        "上海炒货居(丹阳分店)"
      ],
      [
        "徐氏粮油烟酒",
        "便利店",
        "宫廷名糕点(华南店)"
      ],
      [
        "宫廷名糕点(华南店)",
        "蛋糕店",
        "徐氏粮油烟酒"
      ],
      [
        "依恋花屋",
        "花鸟鱼虫市场",
        "宫廷名糕点(华南店)"
      ],
      [
        "宫廷名糕点(华南店)",
        "蛋糕店",
        "依恋花屋"
      ],
      [
        "依恋花屋",
        "花鸟鱼虫市场",
        "手佳推拿馆"
      ],
      [
        "手佳推拿馆",
        "洗浴中心",
        "依恋花屋"
      ],
      [
        "上海炒货居(丹阳分店)",
        "果蔬店",
        "纤秀美容养生馆(华南路店)"
      ],
      [
        "纤秀美容养生馆(华南路店)",
        "理发店",
        "上海炒货居(丹阳分店)"
      ],
      [
        "徐氏粮油烟酒",
        "便利店",
        "纤秀美容养生馆(华南路店)"
      ],
      [
        "纤秀美容养生馆(华南路店)",
        "理发店",
        "徐氏粮油烟酒"
      ],
      [
        "徐氏粮油烟酒",
        "便利店",
        "上海炒货居(丹阳分店)"
      ],
      [
        "上海炒货居(丹阳分店)",
        "果蔬店",
        "徐氏粮油烟酒"
      ],
      [
        "依恋花屋",
        "花鸟鱼虫市场",
        "徐氏粮油烟酒"
      ],
      [
        "徐氏粮油烟酒",
        "便利店",
        "依恋花屋"
      ]
    ],
    "北京市大兴区北京经济技术开发区新康家园(燕景佳园东南)新康家园文化园西路26号": [
      [
        "百旺居",
        "餐厅",
        "北京市大兴区北京经济技术开发区新康家园(燕景佳园东南)新康家园文化园西路26号"
      ],
      [
        "北京稻香村(华冠亦庄店)",
        "蛋糕店",
        "北京市大兴区北京经济技术开发区新康家园(燕景佳园东南)新康家园文化园西路26号"
      ]
    ],
    "重庆市万州区周家坝街道重庆市万州第一人民医院万州区第四人民医院职工宿舍天城东路388号": [
      [
        "元味串串香",
        "餐厅",
        "重庆市万州区周家坝街道重庆市万州第一人民医院万州区第四人民医院职工宿舍天城东路388号"
      ],
      [
        "琪莱宾馆",
        "宾馆酒店",
        "重庆市万州区周家坝街道重庆市万州第一人民医院万州区第四人民医院职工宿舍天城东路388号"
      ],
      [
        "威英副食店",
        "便利店",
        "重庆市万州区周家坝街道重庆市万州第一人民医院万州区第四人民医院职工宿舍天城东路388号"
      ],
      [
        "海利不锈钢管",
        "商场",
        "重庆市万州区周家坝街道重庆市万州第一人民医院万州区第四人民医院职工宿舍天城东路388号"
      ],
      [
        "飘雪音响",
        "数码商城",
        "重庆市万州区周家坝街道重庆市万州第一人民医院万州区第四人民医院职工宿舍天城东路388号"
      ],
      [
        "流水社区",
        "住宅区",
        "重庆市万州区周家坝街道重庆市万州第一人民医院万州区第四人民医院职工宿舍天城东路388号"
      ],
      [
        "重庆三峡银行(天城支行)",
        "银行",
        "重庆市万州区周家坝街道重庆市万州第一人民医院万州区第四人民医院职工宿舍天城东路388号"
      ],
      [
        "黑子水果超市",
        "果蔬店",
        "重庆市万州区周家坝街道重庆市万州第一人民医院万州区第四人民医院职工宿舍天城东路388号"
      ],
      [
        "丽雅美容养身馆",
        "理发店",
        "重庆市万州区周家坝街道重庆市万州第一人民医院万州区第四人民医院职工宿舍天城东路388号"
      ],
      [
        "海利不锈钢管",
        "商场",
        "元味串串香"
      ],
      [
        "元味串串香",
        "餐厅",
        "海利不锈钢管"
      ],
      [
        "流水社区",
        "住宅区",
        "元味串串香"
      ],
      [
        "元味串串香",
        "餐厅",
        "流水社区"
      ],
      [
        "黑子水果超市",
        "果蔬店",
        "元味串串香"
      ],
      [
        "元味串串香",
        "餐厅",
        "黑子水果超市"
      ],
      [
        "丽雅美容养身馆",
        "理发店",
        "元味串串香"
      ],
      [
        "元味串串香",
        "餐厅",
        "丽雅美容养身馆"
      ],
      [
        "威英副食店",
        "便利店",
        "琪莱宾馆"
      ],
      [
        "琪莱宾馆",
        "宾馆酒店",
        "威英副食店"
      ],
      [
        "飘雪音响",
        "数码商城",
        "琪莱宾馆"
      ],
      [
        "琪莱宾馆",
        "宾馆酒店",
        "飘雪音响"
      ],
      [
        "丽雅美容养身馆",
        "理发店",
        "琪莱宾馆"
      ],
      [
        "琪莱宾馆",
        "宾馆酒店",
        "丽雅美容养身馆"
      ],
      [
        "飘雪音响",
        "数码商城",
        "威英副食店"
      ],
      [
        "威英副食店",
        "便利店",
        "飘雪音响"
      ],
      [
        "丽雅美容养身馆",
        "理发店",
        "威英副食店"
      ],
      [
        "威英副食店",
        "便利店",
        "丽雅美容养身馆"
      ],
      [
        "流水社区",
        "住宅区",
        "海利不锈钢管"
      ],
      [
        "海利不锈钢管",
        "商场",
        "流水社区"
      ],
      [
        "黑子水果超市",
        "果蔬店",
        "海利不锈钢管"
      ],
      [
        "海利不锈钢管",
        "商场",
        "黑子水果超市"
      ],
      [
        "丽雅美容养身馆",
        "理发店",
        "飘雪音响"
      ],
      [
        "飘雪音响",
        "数码商城",
        "丽雅美容养身馆"
      ],
      [
        "黑子水果超市",
        "果蔬店",
        "流水社区"
      ],
      [
        "流水社区",
        "住宅区",
        "黑子水果超市"
      ],
      [
        "丽雅美容养身馆",
        "理发店",
        "黑子水果超市"
      ],
      [
        "黑子水果超市",
        "果蔬店",
        "丽雅美容养身馆"
      ]
    ]
  }
}